releases/__init__.py
releases/_version.py
releases/line_manager.py
releases/models.py
releases/util.py
releases-2.1.1.dist-info/LICENSE
releases-2.1.1.dist-info/METADATA
releases-2.1.1.dist-info/WHEEL
releases-2.1.1.dist-info/top_level.txt
releases-2.1.1.dist-info/RECORD
