Metadata-Version: 2.1
Name: releases
Version: 2.1.1
Summary: A Sphinx extension for changelog manipulation
Home-page: https://github.com/bitprophet/releases
Author: Jeff Forcier
Author-email: jeff@bitprophet.org
License: UNKNOWN
Project-URL: Docs, https://releases.readthedocs.io
Project-URL: Source, https://github.com/bitprophet/releases
Project-URL: Changelog, https://releases.readthedocs.io/en/latest/changelog.html
Project-URL: CI, https://app.circleci.com/pipelines/github/bitprophet/releases
Platform: UNKNOWN
Classifier: Development Status :: 5 - Production/Stable
Classifier: Intended Audience :: Developers
Classifier: License :: OSI Approved :: BSD License
Classifier: Operating System :: MacOS :: MacOS X
Classifier: Operating System :: Unix
Classifier: Operating System :: POSIX
Classifier: Operating System :: Microsoft :: Windows
Classifier: Programming Language :: Python
Classifier: Programming Language :: Python :: 3
Classifier: Programming Language :: Python :: 3 :: Only
Classifier: Programming Language :: Python :: 3.6
Classifier: Programming Language :: Python :: 3.7
Classifier: Programming Language :: Python :: 3.8
Classifier: Programming Language :: Python :: 3.9
Classifier: Programming Language :: Python :: 3.10
Classifier: Programming Language :: Python :: 3.11
Classifier: Topic :: Software Development
Classifier: Topic :: Software Development :: Documentation
Classifier: Topic :: Documentation
Classifier: Topic :: Documentation :: Sphinx
Requires-Python: >=3.6
Requires-Dist: sphinx (>=4)
Requires-Dist: semantic-version (<2.7)
